finance_etc/__init__.py
finance_etc/csv_source_parser.py
finance_etc/duckdb_tax_func.py
finance_etc/mortgage.py
finance_etc/myutils.py
finance_etc-0.1.1.dist-info/METADATA
finance_etc-0.1.1.dist-info/WHEEL
finance_etc-0.1.1.dist-info/RECORD
